deepcheck/__init__.py
deepcheck/library.py
deepcheck-0.12.dist-info/LICENSE.txt
deepcheck-0.12.dist-info/METADATA
deepcheck-0.12.dist-info/WHEEL
deepcheck-0.12.dist-info/top_level.txt
deepcheck-0.12.dist-info/RECORD
