Metadata-Version: 2.1
Name: deepcheck
Version: 0.12
Summary: Build and release task for determining neural network susceptibility to adversarial machine learning
Home-page: UNKNOWN
Author: TeamDeepCheck
Author-email: UNKNOWN
License: GPL
Keywords: pip,adversarial machine learning,deep learning
Platform: UNKNOWN
Requires-Dist: numpy
Requires-Dist: scipy
Requires-Dist: six
Requires-Dist: scikit-learn
Requires-Dist: Adversarial-Robustness-Toolbox (==0.5.0)
Requires-Dist: keras
Requires-Dist: tensorflow
Requires-Dist: Pillow
Requires-Dist: BeautifulTable
